{
	"__comment": "Designed by CityOfSkyTCD",
	"parent": "minecraft:block/block",
	"ambientocclusion": false,
	"textures": {
		"particle": "chineseworkshop:block/stone_tower_lamp",
		"texture": "chineseworkshop:block/candle_s"
	},
	"elements": [
		{
			"from": [ 6, 1, 10 ],
			"to": [ 10, 2, 11 ],
			"faces": {
				"down": { "uv": [ 4, 7, 10, 8 ], "texture": "#particle" },
				"up": { "uv": [ 4, 7, 10, 8 ], "texture": "#particle" },
				"north": { "uv": [ 2, 8, 6, 9 ], "texture": "#particle" },
				"south": { "uv": [ 5, 7, 11, 8 ], "texture": "#particle" },
				"west": { "uv": [ 9, 7, 10, 8 ], "texture": "#particle" },
				"east": { "uv": [ 8, 7, 9, 8 ], "texture": "#particle" }
			}
		},
		{
			"from": [ 10, 1, 6 ],
			"to": [ 11, 2, 10 ],
			"faces": {
				"down": { "uv": [ 7, 8, 8, 14 ], "texture": "#particle" },
				"up": { "uv": [ 11, 7, 12, 8 ], "texture": "#particle" },
				"north": { "uv": [ 9, 7, 10, 8 ], "texture": "#particle" },
				"south": { "uv": [ 8, 7, 9, 8 ], "texture": "#particle" },
				"west": { "uv": [ 4, 8, 5, 9 ], "texture": "#particle" },
				"east": { "uv": [ 4, 7, 10, 8 ], "texture": "#particle" }
			}
		},
		{
			"from": [ 6, 1, 5 ],
			"to": [ 10, 2, 6 ],
			"faces": {
				"down": { "uv": [ 4, 7, 10, 8 ], "texture": "#particle" },
				"up": { "uv": [ 4, 7, 10, 8 ], "texture": "#particle" },
				"north": { "uv": [ 5, 7, 11, 8 ], "texture": "#particle" },
				"south": { "uv": [ 4, 8, 6, 9 ], "texture": "#particle" },
				"west": { "uv": [ 3, 7, 4, 8 ], "texture": "#particle" },
				"east": { "uv": [ 4, 7, 5, 8 ], "texture": "#particle" }
			}
		},
		{
			"from": [ 5, 1, 6 ],
			"to": [ 6, 2, 10 ],
			"faces": {
				"down": { "uv": [ 7, 8, 8, 14 ], "texture": "#particle" },
				"up": { "uv": [ 4, 7, 5, 8 ], "texture": "#particle" },
				"north": { "uv": [ 3, 7, 4, 8 ], "texture": "#particle" },
				"south": { "uv": [ 4, 7, 5, 8 ], "texture": "#particle" },
				"west": { "uv": [ 5, 7, 11, 8 ], "texture": "#particle" },
				"east": { "uv": [ 5, 8, 7, 9 ], "texture": "#particle" }
			}
		},
		{
			"from": [ 7.5, 1, 7.5 ],
			"to": [ 8.5, 6, 8.5 ],
			"faces": {
				"up": { "uv": [ 14, 10, 15, 11 ], "texture": "#particle" },
				"north": { "uv": [ 14, 10, 15, 11 ], "texture": "#particle" },
				"south": { "uv": [ 14, 10, 15, 11 ], "texture": "#particle" },
				"west": { "uv": [ 14, 10, 15, 11 ], "texture": "#particle" },
				"east": { "uv": [ 14, 10, 15, 11 ], "texture": "#particle" }
			}
		},
		{
			"__comment": "PlaneX14",
			"from": [ 8, 6, 7.5 ],
			"to": [ 8.001, 8, 8.5 ],
			"faces": {
				"west": { "uv": [ 8, 11, 10.5, 16 ], "texture": "#texture" },
				"east": { "uv": [ 10.5, 11, 8, 16 ], "texture": "#texture" }
			}
		},
		{
			"from": [ 6, 0, 6 ],
			"to": [ 10, 1, 10 ],
			"faces": {
				"down": { "uv": [ 3, 8, 6, 9 ], "texture": "#particle" },
				"up": { "uv": [ 1, 8, 2, 9 ], "texture": "#particle" },
				"north": { "uv": [ 4, 8, 6, 9 ], "texture": "#particle" },
				"south": { "uv": [ 2, 8, 6, 9 ], "texture": "#particle" },
				"west": { "uv": [ 1, 8, 7, 9 ], "texture": "#particle" },
				"east": { "uv": [ 3, 8, 5, 9 ], "texture": "#particle" }
			}
		}
	]
}